{
  "updated": "2026-05-29T23:59:21.288Z",
  "errors": [],
  "yields": {
    "date": "05/29/2026",
    "us2y": 3.98,
    "us10y": 4.45,
    "us30y": 4.99,
    "source": "US Treasury (daily par yield)"
  },
  "crypto": {
    "btc_usd": 73386,
    "btc_24h_pct": -0.2089822836025298,
    "eth_usd": 2012.08,
    "eth_24h_pct": 0.22498794403845124,
    "source": "CoinGecko"
  },
  "stocks_oil": {
    "spx": 7580.1,
    "ndx": 26972.62,
    "dji": 51032.5,
    "wti": 87.76,
    "brent": 91.59,
    "asof": "2026-05-29",
    "source": "stooq"
  },
  "fed": {
    "title": "How many Fed rate cuts in 2026?",
    "zero_cuts_prob": 0.6725,
    "outcomes": {
      "0": 0.6725,
      "1": 0.185,
      "2": 0.075,
      "3": 0.0315,
      "4": 0.0135,
      "5": 0.007,
      "6": 0.0045,
      "7": 0.0035,
      "8": 0.0035,
      "9": 0.0045,
      "10": 0.0025,
      "11": 0.0025,
      "12": 0.0035
    },
    "source": "Polymarket"
  }
}